nrefocus/__init__.py
nrefocus/_version.py
nrefocus/_version_save.py
nrefocus/autof.py
nrefocus/legacy.py
nrefocus/pad.py
nrefocus/propg.py
nrefocus/roi_handling.py
nrefocus/iface/__init__.py
nrefocus/iface/base.py
nrefocus/iface/rf_numpy.py
nrefocus/iface/rf_numpy_1d.py
nrefocus/iface/rf_pyfftw.py
nrefocus/metrics/__init__.py
nrefocus/metrics/mt_avg_grad.py
nrefocus/metrics/mt_med_grad.py
nrefocus/metrics/mt_rms_contrast.py
nrefocus/metrics/mt_spectrum.py
nrefocus/metrics/mt_std_grad.py
nrefocus/minimizers/__init__.py
nrefocus/minimizers/mz_legacy.py
nrefocus/minimizers/mz_lmfit.py
nrefocus-0.5.3.dist-info/LICENSE
nrefocus-0.5.3.dist-info/METADATA
nrefocus-0.5.3.dist-info/WHEEL
nrefocus-0.5.3.dist-info/top_level.txt
nrefocus-0.5.3.dist-info/RECORD
