Metadata-Version: 2.1
Name: nrefocus
Version: 0.5.3
Summary: numerical focusing (refocusing, autofocusing) of complex wave fields
Home-page: https://github.com/RI-imaging/nrefocus
Author: Paul Müller
Author-email: dev@craban.de
License: BSD (3 clause)
Keywords: autofocus,refocus,numerical focusing,quantitative phase imaging,digital holographic microscopy
Platform: ALL
Classifier: Operating System :: OS Independent
Classifier: Programming Language :: Python :: 3
Classifier: Intended Audience :: Science/Research
Requires-Python: >=3.6, <4
License-File: LICENSE
Requires-Dist: lmfit
Requires-Dist: numexpr
Requires-Dist: numpy (>=1.5.1)
Provides-Extra: fftw
Requires-Dist: pyfftw (>=0.12.0) ; extra == 'fftw'
